LICENSE
MANIFEST.in
setup.cfg
setup.py
barmanapi/__init__.py
barmanapi/app.py
barmanapi/auth.py
barmanapi/barmanapi.py
barmanapi/baseexception.py
barmanapi/config.py
barmanapi/history.py
barmanapi/parser.py
barmanapi/version.py
barmanapi.egg-info/PKG-INFO
barmanapi.egg-info/SOURCES.txt
barmanapi.egg-info/dependency_links.txt
barmanapi.egg-info/requires.txt
barmanapi.egg-info/top_level.txt
bin/barmanapi
config/barmanapi.conf
config/client.conf
config/man.conf
config/template/config_change_template