Metadata-Version: 1.1
Name: barmanapi
Version: 0.2
Summary: This project convert from BARMAN command to RESTful api. Barman API support full future and all versions of BARMAN.
Home-page: https://github.com/emin100/barmanapi
Author: Mehmet Emin KARAKAS
Author-email: emin100@gmail.com
License: GPL-3.0
Keywords: barmanapi Rest api barman
Platform: Linux
Platform: Mac OS X
Classifier: Environment :: Console
Classifier: Development Status :: 5 - Production/Stable
Classifier: Topic :: System :: Archiving :: Backup
Classifier: Topic :: Database
Classifier: Topic :: System :: Recovery Tools
Classifier: Topic :: Internet :: WWW/HTTP :: WSGI :: Middleware
Classifier: Intended Audience :: System Administrators
Classifier: License :: OSI Approved :: GNU General Public License v3 or later (GPLv3+)
Classifier: Programming Language :: Python
Classifier: Programming Language :: Python :: 2.6
Classifier: Programming Language :: Python :: 2.7
Classifier: Programming Language :: Python :: 3.3
Classifier: Programming Language :: Python :: 3.4
Classifier: Programming Language :: Python :: 3.5
Classifier: Framework :: Flask
Classifier: Natural Language :: English
